gocdpb/__init__.py
gocdpb/gocd_settings.py
gocdpb/gocdpb.py
gocdpb/goserver_adapter.py
gocdpb/goserver_config.py
gocdpb/test_gocdrepos.py
gocdpb-3.dist-info/DESCRIPTION.rst
gocdpb-3.dist-info/METADATA
gocdpb-3.dist-info/RECORD
gocdpb-3.dist-info/WHEEL
gocdpb-3.dist-info/entry_points.txt
gocdpb-3.dist-info/metadata.json
gocdpb-3.dist-info/top_level.txt
